[
  {"id":"geng","name":"Gen.G","region":"LCK","logo":"https://placehold.co/64x64/111827/facc15?text=GEN","primaryColor":"#facc15","secondaryColor":"#111827","prefStrategy":"Late","prefLabel":"후반 밸류 조합"},
  {"id":"t1","name":"T1","region":"LCK","logo":"https://placehold.co/64x64/111111/e5e7eb?text=T1","primaryColor":"#e53935","secondaryColor":"#111111","prefStrategy":"Dive","prefLabel":"돌진 조합"},
  {"id":"hle","name":"Hanwha Life Esports","region":"LCK","logo":"https://placehold.co/64x64/111827/f97316?text=HLE","primaryColor":"#f97316","secondaryColor":"#111827","prefStrategy":"Early","prefLabel":"초반 조합"},
  {"id":"dk","name":"Dplus KIA","region":"LCK","logo":"https://placehold.co/64x64/0f172a/60a5fa?text=DK","primaryColor":"#60a5fa","secondaryColor":"#0f172a","prefStrategy":"Mid","prefLabel":"중반 조합"},
  {"id":"kt","name":"KT Rolster","region":"LCK","logo":"https://placehold.co/64x64/111827/f43f5e?text=KT","primaryColor":"#f43f5e","secondaryColor":"#111827","prefStrategy":"Mid","prefLabel":"중반 조합"},
  {"id":"ns","name":"Nongshim RedForce","region":"LCK","logo":"https://placehold.co/64x64/1f2937/f87171?text=NS","primaryColor":"#f87171","secondaryColor":"#1f2937","prefStrategy":"Late","prefLabel":"후반 밸류 조합"},
  {"id":"dnf","name":"DN SOOP","region":"LCK","logo":"https://placehold.co/64x64/0f172a/22d3ee?text=DN","primaryColor":"#22d3ee","secondaryColor":"#0f172a","prefStrategy":"Dive","prefLabel":"돌진 조합"},
  {"id":"bfx","name":"BNK FEARX","region":"LCK","logo":"https://placehold.co/64x64/111827/a3e635?text=BFX","primaryColor":"#a3e635","secondaryColor":"#111827","prefStrategy":"Early","prefLabel":"초반 조합"},
  {"id":"drx","name":"DRX","region":"LCK","logo":"https://placehold.co/64x64/0b132b/38bdf8?text=DRX","primaryColor":"#38bdf8","secondaryColor":"#0b132b","prefStrategy":"Dive","prefLabel":"돌진 조합"},
  {"id":"bro","name":"OK BRION","region":"LCK","logo":"https://placehold.co/64x64/14532d/86efac?text=BRO","primaryColor":"#86efac","secondaryColor":"#14532d","prefStrategy":"Anti","prefLabel":"받아치기 조합"},

  {"id":"blg","name":"BLG","region":"LPL","logo":"https://placehold.co/64x64/1b1b1b/f87171?text=BLG","primaryColor":"#f87171","secondaryColor":"#1b1b1b","prefStrategy":"Dive","prefLabel":"돌진 조합"},
  {"id":"tes","name":"TES","region":"LPL","logo":"https://placehold.co/64x64/111827/f59e0b?text=TES","primaryColor":"#f59e0b","secondaryColor":"#111827","prefStrategy":"Dive","prefLabel":"돌진 조합"},
  {"id":"wbg","name":"WBG","region":"LPL","logo":"https://placehold.co/64x64/111827/f97316?text=WBG","primaryColor":"#f97316","secondaryColor":"#111827","prefStrategy":"Mid","prefLabel":"중반 조합"},
  {"id":"jdg","name":"JDG","region":"LPL","logo":"https://placehold.co/64x64/111827/facc15?text=JDG","primaryColor":"#facc15","secondaryColor":"#111827","prefStrategy":"Late","prefLabel":"후반 밸류 조합"},

  {"id":"g2","name":"G2 Esports","region":"LEC","logo":"https://placehold.co/64x64/0f172a/60a5fa?text=G2","primaryColor":"#60a5fa","secondaryColor":"#0f172a","prefStrategy":"Mid","prefLabel":"중반 조합"},
  {"id":"fnc","name":"Fnatic","region":"LEC","logo":"https://placehold.co/64x64/111827/f97316?text=FNC","primaryColor":"#f97316","secondaryColor":"#111827","prefStrategy":"Dive","prefLabel":"돌진 조합"},
  {"id":"kc","name":"Karmine Corp","region":"LEC","logo":"https://placehold.co/64x64/0b1020/3b82f6?text=KC","primaryColor":"#3b82f6","secondaryColor":"#0b1020","prefStrategy":"Early","prefLabel":"초반 조합"},

  {"id":"c9","name":"Cloud9","region":"LTA","logo":"https://placehold.co/64x64/082f49/7dd3fc?text=C9","primaryColor":"#7dd3fc","secondaryColor":"#082f49","prefStrategy":"Poke","prefLabel":"포킹 조합"},
  {"id":"tl","name":"Team Liquid","region":"LTA","logo":"https://placehold.co/64x64/0f172a/e5e7eb?text=TL","primaryColor":"#e5e7eb","secondaryColor":"#0f172a","prefStrategy":"Mid","prefLabel":"중반 조합"},
  {"id":"fly","name":"FlyQuest","region":"LTA","logo":"https://placehold.co/64x64/14532d/86efac?text=FLY","primaryColor":"#86efac","secondaryColor":"#14532d","prefStrategy":"Late","prefLabel":"후반 밸류 조합"}
]
